photon_platform/formulator/__init__.py
photon_platform/formulator/app.py
photon_platform/formulator/composer.py
photon_platform/formulator/formulator.css
photon_platform/formulator/formulator.py
photon_platform/formulator/modal.py
photon_platform/formulator/validator.py
photon_platform_formulator-0.0.3.dist-info/LICENSE
photon_platform_formulator-0.0.3.dist-info/METADATA
photon_platform_formulator-0.0.3.dist-info/WHEEL
photon_platform_formulator-0.0.3.dist-info/entry_points.txt
photon_platform_formulator-0.0.3.dist-info/top_level.txt
photon_platform_formulator-0.0.3.dist-info/RECORD
