Metadata-Version: 2.1
Name: photon-platform-formulator
Version: 0.0.3
Summary: create and manage log entries for a python project
Author-email: phi ARCHITECT <github@phiarchitect.com>
Project-URL: Homepage, https://github.com/photon-platform/formulator
Project-URL: Bug Tracker, https://github.com/photon-platform/formulator/issues
Classifier: Programming Language :: Python :: 3
Classifier: License :: OSI Approved :: MIT License
Classifier: Operating System :: OS Independent
Requires-Python: >=3.7
License-File: LICENSE
Requires-Dist: textual
Requires-Dist: rich
Requires-Dist: jinja2
